<?xml version="1.0" encoding="utf-8" ?>
<litepal>
    <dbname value="ReaderLater"></dbname>
    <version value="1"></version>

    <list>
        <mapping class="com.zhaoyanyang.multiplenewsreader.ContextUtils.Readlater"></mapping>
        <mapping class="com.zhaoyanyang.multiplenewsreader.ContextUtils.HateNews"></mapping>
        <mapping class="com.zhaoyanyang.multiplenewsreader.ContextUtils.LikeBean"></mapping>
        <mapping class="com.zhaoyanyang.multiplenewsreader.ContextUtils.hadread"></mapping>
    </list>
</litepal>